mappls_map_widget/__init__.py
mappls_map_widget/apps.py
mappls_map_widget/widgets.py
mappls_map_widget/templates/__init__.py
mappls_map_widget/templates/mappls_pin_with_embed_widget.html
mappls_map_widget-0.1.1.dist-info/licenses/LICENSE
mappls_map_widget-0.1.1.dist-info/METADATA
mappls_map_widget-0.1.1.dist-info/WHEEL
mappls_map_widget-0.1.1.dist-info/top_level.txt
mappls_map_widget-0.1.1.dist-info/RECORD
