Metadata-Version: 2.4
Name: mappls-map-widget
Version: 0.1.1
Summary: Mappls Map Widget for Django
Home-page: https://github.com/soumayg9673/mappls-django
Author: Soumay Gupta
Author-email: Soumay Gupta <pmrs9673@gmail.com>
License-Expression: MIT
Project-URL: Homepage, https://github.com/soumayg9673/mappls-django
Classifier: Framework :: Django
Classifier: Programming Language :: Python :: 3
Classifier: Operating System :: OS Independent
Requires-Python: >=3.7
License-File: LICENSE
Requires-Dist: Django>=3.2
Dynamic: author
Dynamic: home-page
Dynamic: license-file
Dynamic: requires-python
